timescoring/__init__.py
timescoring/annotations.py
timescoring/scoring.py
timescoring/visualization.py
timescoring-0.0.7.dist-info/METADATA
timescoring-0.0.7.dist-info/WHEEL
timescoring-0.0.7.dist-info/licenses/LICENSE
timescoring-0.0.7.dist-info/RECORD
