Metadata-Version: 2.4
Name: timescoring
Version: 0.0.7
Summary: Library for measuring performance of time series classification
Project-URL: Homepage, https://github.com/esl-epfl/epilepsy_performance_metrics
Project-URL: Bug Tracker, https://github.com/esl-epfl/epilepsy_performance_metrics/issues
Author: PEDESITE
Author-email: Jonathan Dan <jonathan.dan@epfl.ch>, Una Pale <una.pale@epfl.ch>
License-File: LICENSE
Requires-Python: >=3.10
Requires-Dist: numpy>=1.24.3
